{"user": {"name": "Clt_TrafficGuy", "id_str": "485608474"}, "text": "\u25bc\u25bc#Downtown #Matthews is the spot to #AVOID this morning.\nA Gas Leak has John St SHUT DOWN.\n#Charlotte #Traffic #Clt", "created_at": "Mon Oct 26 09:05:54 +0000 2015", "id_str": "658570234136252417", "timestamp_ms": "1445850354000"}
{"user": {"name": "totaltrafficclt", "id_str": "54283257"}, "text": "Gas leak, caution in #DowntownMatthews on E John St between Trade St and Hwy 51 #traffic http://bit.ly/12qKnl0\u00a0", "created_at": "Mon Oct 26 09:05:08 +0000 2015", "id_str": "658570041370132482", "timestamp_ms": "1445850308000"}
