{"user": {"name": "guenth11", "id_str": "340977489"}, "text": "the unmanned blimp caused the power outage in bloom?", "created_at": "Wed Oct 28 18:38:38 +0000 2015", "id_str": "659439146507902976", "timestamp_ms": "1446057518000"}
{"user": {"name": "outagecentral", "id_str": "128804425"}, "text": "Crews still working on restoring power throughout Hampton Roads - WAVY-TV: WAVY-TVCrews still wor... http://bit.ly/1kb827b\u00a0 #poweroutage", "created_at": "Wed Oct 28 18:38:37 +0000 2015", "id_str": "659439140639916032", "timestamp_ms": "1446057517000"}
{"user": {"name": "outagecentral", "id_str": "128804425"}, "text": "Sky Condos residents ticked off about long-term power outage - KTNV Las Vegas: KTNV Las VegasSky ... http://bit.ly/1jRNYax\u00a0 #poweroutage", "created_at": "Wed Oct 28 18:38:37 +0000 2015", "id_str": "659439139893346304", "timestamp_ms": "1446057517000"}
