{"user": {"name": "asvpstratford", "id_str": "414617487"}, "text": "FUCK THIS POWER OUTAGE MAN DENNY'S IS CLOSED, JACK IN THE BOX, MCDONALD'S, PIZZA HUT, E V E R Y T H I N G", "created_at": "Tue Oct 27 03:12:48 +0000 2015", "id_str": "658843761733054464", "timestamp_ms": "1445915568000"}
{"user": {"name": "WWLTV", "id_str": "14269771"}, "text": "Businesses left in dark during Uptown power outage\n http://www.wwltv.com/story/news/local/orleans/2015/10/26/uptown-drainage-project-slows-entergy-turning-power-back-on/74663320/\u00a0\u2026", "created_at": "Tue Oct 27 03:12:42 +0000 2015", "id_str": "658843737443991556", "timestamp_ms": "1445915562000"}
