{"user": {"name": "carsonautri", "id_str": "1152424957"}, "text": "Power outage update: I am not wearing shoes.", "created_at": "Fri Oct 23 14:34:53 +0000 2015", "id_str": "657565865496281089", "timestamp_ms": "1445610893000"}
{"user": {"name": "catpatg", "id_str": "3730693094"}, "text": "power outage update: \"I'm gonna become a professional hangman\"", "created_at": "Fri Oct 23 14:34:47 +0000 2015", "id_str": "657565840355627009", "timestamp_ms": "1445610887000"}
{"user": {"name": "liveair", "id_str": "19667195"}, "text": "Network Alert: Grid Power outage in Fayetteville area is affecting east Fayette County and West Colorado County... http://fb.me/SFVamsCX\u00a0", "created_at": "Fri Oct 23 14:34:41 +0000 2015", "id_str": "657565812752973824", "timestamp_ms": "1445610881000"}
