{"user": {"name": "MarcieHudgins", "id_str": "498835231"}, "text": "@DarciWLTX can u help us clarify congaree bridge closure 601- is Calhoun cty or Richlnd cty side/tryin to reach St Matthews-list not specifc", "created_at": "Wed Oct 07 16:01:52 +0000 2015", "id_str": "651789548092063744", "timestamp_ms": "1444233712000"}
{"user": {"name": "DavidJ_McCann", "id_str": "24516723"}, "text": "Police Scotland has changed closure times for Forth Bridge and M90 THREE times in an hour following controlled explosion announcement...", "created_at": "Wed Oct 07 16:01:12 +0000 2015", "id_str": "651789378570878977", "timestamp_ms": "1444233672000"}
{"user": {"name": "fiona_90", "id_str": "32892746"}, "text": "Fiona Pollock Retweeted Forth Road Bridge", "created_at": "Wed Oct 07 16:01:07 +0000 2015", "id_str": "651789359386071040", "timestamp_ms": "1444233667000"}
