{"user": {"name": "MultiCultural7", "id_str": "48120617"}, "text": "Belmont Shore-Naples Patch: Power Outage Causes Major Blue Line Delays http://patch.com/california/belmontshore/power-outage-causes-major-blue-line-delays\u00a0\u2026", "created_at": "Sat Oct 31 01:38:21 +0000 2015", "id_str": "660269545026785280", "timestamp_ms": "1446255501000"}
{"user": {"name": "alana_ippolito", "id_str": "1959753678"}, "text": "Very convenient to have a power outage in the last 14 seconds #nicewinboys ", "created_at": "Sat Oct 31 01:38:13 +0000 2015", "id_str": "660269511367630848", "timestamp_ms": "1446255493000"}
