{"user": {"name": "HCCFL", "id_str": "79538332"}, "text": "HCC data center had a power outage. We are working to restore all systems. (1/2)", "created_at": "Tue Oct 27 22:11:54 +0000 2015", "id_str": "659130427085619200", "timestamp_ms": "1445983914000"}
{"user": {"name": "RedDoubleBlue", "id_str": "2239760269"}, "text": "Power best not come back on too soon. I got the wife picking up supper ! She'll b mad if I was just feining a power outage for take out!", "created_at": "Tue Oct 27 22:11:00 +0000 2015", "id_str": "659130202451288064", "timestamp_ms": "1445983860000"}
