{"user": {"name": "outagecentral", "id_str": "128804425"}, "text": "Power outage affects 1100 - Sioux Falls Argus Leader: Power outage affects 1100Sioux Falls Argus ... http://bit.ly/1ijgLmM\u00a0 #poweroutage", "created_at": "Wed Oct 28 21:37:07 +0000 2015", "id_str": "659484060897513472", "timestamp_ms": "1446068227000"}
{"user": {"name": "outagecentral", "id_str": "128804425"}, "text": "Runaway NORAD blimp spotted over Bloomsburg, PA; widespread power outage reported - Allentown Mor... http://bit.ly/1ijgLmE\u00a0 #poweroutage", "created_at": "Wed Oct 28 21:37:07 +0000 2015", "id_str": "659484060008345600", "timestamp_ms": "1446068227000"}
