{"user": {"name": "7News", "id_str": "16558796"}, "text": "NOW: Bristol-Plymouth Regional Technical High School is closed for the day due to a power outage #7News", "created_at": "Thu Oct 29 10:30:47 +0000 2015", "id_str": "659678759365292032", "timestamp_ms": "1446114647000"}
{"user": {"name": "TWCNewsAlbany", "id_str": "26676275"}, "text": "#NorthAdamsMA was hit hardest in Wednesday night's temporary #Berkshires power outage: http://www.twcnews.com/nys/capital-region/news/2015/10/28/north-adams-hit-hardest-in-berkshire-county-power-outage.html?cid=twitter_TWCNewsAlbany\u00a0\u2026", "created_at": "Thu Oct 29 10:30:16 +0000 2015", "id_str": "659678629199130624", "timestamp_ms": "1446114616000"}
