{"user": {"name": "jensheerio", "id_str": "37627459"}, "text": "Traffic lights were out and the girl next to me shrugged at me and i shrugged back #whentogo #indecisive", "created_at": "Tue Oct 06 06:30:44 +0000 2015", "id_str": "651283427723837440", "timestamp_ms": "1444113044000"}
{"user": {"name": "MeMissHarrison", "id_str": "2587412424"}, "text": "@AkiAnastasiou Traffic lights out at Witkoppen and Main roads", "created_at": "Tue Oct 06 06:30:04 +0000 2015", "id_str": "651283261814087680", "timestamp_ms": "1444113004000"}
