{"user": {"name": "KieranSweeney91", "id_str": "21362647"}, "text": "you know you're like a gas leak?! we can't smell you, we can't see you, but you're slowly killing us all", "created_at": "Mon Oct 26 19:36:59 +0000 2015", "id_str": "658729052451307520", "timestamp_ms": "1445888219000"}
{"user": {"name": "bnndesk", "id_str": "15534315"}, "text": "#BreakingNews Gas Leak - Manhattan, NY: FD reports a gas leak at a construction site. #920324 http://facebook.com/bnndesk\u00a0", "created_at": "Mon Oct 26 19:36:37 +0000 2015", "id_str": "658728958872064000", "timestamp_ms": "1445888197000"}
{"user": {"name": "BreakingNewsNY", "id_str": "11290602"}, "text": "#BreakingNews Gas Leak - Manhattan, NY: FD reports a gas leak at a construction site. #920324 http://facebook.com/bnndesk\u00a0", "created_at": "Mon Oct 26 19:36:33 +0000 2015", "id_str": "658728946003935232", "timestamp_ms": "1445888193000"}
