{"user": {"name": "DrewDoughtyFans", "id_str": "615208392"}, "text": "Power Outage Pulls Plug on Kings Hockey Practice http://www.snsanalytics.com/I2mSy2\u00a0", "created_at": "Thu Oct 22 04:30:48 +0000 2015", "id_str": "657051451034877952", "timestamp_ms": "1445488248000"}
{"user": {"name": "FutureITouch", "id_str": "1270440792"}, "text": "How to keep your gear on in a blackout #tech #solar #emergency #blackout #poweroutage #gadgets #emergencyplanning http://ow.ly/TGnc1\u00a0", "created_at": "Thu Oct 22 04:30:41 +0000 2015", "id_str": "657051425344757760", "timestamp_ms": "1445488241000"}
