{"user": {"name": "SNNreporter", "id_str": "417838686"}, "text": "Mulaudzi: The person who was removed is in critical conditions, he suffers from head and spine injuries @ANN7tv #BridgeCollapse  #Dstv405", "created_at": "Wed Oct 14 17:18:50 +0000 2015", "id_str": "654345630731628545", "timestamp_ms": "1444843130000"}
{"user": {"name": "Blackflava", "id_str": "64994697"}, "text": "You would think that the loss of life after the Sandton #BridgeCollapse  would make #Murray&Roberts come out and address the media!", "created_at": "Wed Oct 14 17:18:40 +0000 2015", "id_str": "654345588813758464", "timestamp_ms": "1444843120000"}
{"user": {"name": "tflavour", "id_str": "86919663"}, "text": "The Grayston Drive Bridge collapse is thee Horrendous incident I've seen in a while  No one deserve to die like that", "created_at": "Wed Oct 14 17:18:22 +0000 2015", "id_str": "654345516130635776", "timestamp_ms": "1444843102000"}
{"user": {"name": "Sandton_News", "id_str": "185105271"}, "text": "WATCH: M1 #BridgeCollapse \u2013 @CityofJoburgZA Mayor speaks out  http://bit.ly/1LtR7au\u00a0 @ParksTauCOJ @looklocalsa pic.twitter.com/iKyNaeRebX", "created_at": "Wed Oct 14 17:18:19 +0000 2015", "id_str": "654345502935416832", "timestamp_ms": "1444843099000"}
{"user": {"name": "ewnreporter", "id_str": "191795989"}, "text": "[WATCH] #BridgeCollapse #GraystonBridgeCollapse @EWNTraffic gives you an update on traffic around the M1 pic.twitter.com/PLZ8mV2TCc", "created_at": "Wed Oct 14 17:18:18 +0000 2015", "id_str": "654345497814167552", "timestamp_ms": "1444843098000"}
{"user": {"name": "ANN7tv", "id_str": "1164056179"}, "text": "2nd person rescued from the rubble is in critical condition EMS' Robert Mulaudzi confirms #BridgeCollapse pic.twitter.com/Pk4WcEyCJm", "created_at": "Wed Oct 14 17:18:15 +0000 2015", "id_str": "654345484119707648", "timestamp_ms": "1444843095000"}
{"user": {"name": "JohannesbuRRg", "id_str": "2898586728"}, "text": "VIDEO: Chaos in aftermath of Grayston bridge collapse on M1, Joburg http://www.rightrelevance.com/search/articles/hero?article=d5e02645d90455b1eaaacb8a5b9a9806e59d7f73&query=johannesburg%20south%20africa&taccount=johannesburrg\u00a0\u2026 pic.twitter.com/HDBndcay0E", "created_at": "Wed Oct 14 17:18:05 +0000 2015", "id_str": "654345442088513536", "timestamp_ms": "1444843085000"}
{"user": {"name": "jonahboat", "id_str": "583072377"}, "text": "Blaming #BridgeCollapse on #etolls? Do you still believe in the tooth fairy? Or that the earth popped into being on 11:30 Wed Apr 1 4072BC?", "created_at": "Wed Oct 14 17:18:04 +0000 2015", "id_str": "654345438787727364", "timestamp_ms": "1444843084000"}
{"user": {"name": "Bongiwe_Khumalo", "id_str": "29697325"}, "text": "#BridgeCollapse EMS confirms that the death toll is still at two. The body trapped is actually one of the two @eNCA", "created_at": "Wed Oct 14 17:18:01 +0000 2015", "id_str": "654345427161104384", "timestamp_ms": "1444843081000"}
