{"user": {"name": "outagecentral", "id_str": "128804425"}, "text": "Power outage leaves 55700 in dark - KSBW The Central Coast: KSBW The Central CoastPower outage le... http://bit.ly/1jOzKXs\u00a0 #poweroutage", "created_at": "Sun Oct 18 19:51:09 +0000 2015", "id_str": "655833516672839680", "timestamp_ms": "1445197869000"}
{"user": {"name": "outagecentral", "id_str": "128804425"}, "text": "Car accident causes power outage in Wilbraham - http://MassLive.com\u00a0: MassLive.comCar accident c... http://bit.ly/1PrrCte\u00a0 #poweroutage", "created_at": "Sun Oct 18 19:51:09 +0000 2015", "id_str": "655833515817197568", "timestamp_ms": "1445197869000"}
