{"user": {"name": "WKBW", "id_str": "23686162"}, "text": "UPDATE: Transit Rd now open in both directions between Walden and Broadway. National Fuel says leak contained: http://bit.ly/209QdGI\u00a0", "created_at": "Wed Oct 28 12:41:49 +0000 2015", "id_str": "659349349223243777", "timestamp_ms": "1446036109000"}
{"user": {"name": "CaitlinM_Echo", "id_str": "351052454"}, "text": "UPDATE: Ringwood Road in Ferndown closed due to gas leak at new M&S development (From Bournemouth Echo) http://ow.ly/TWCkJ\u00a0", "created_at": "Wed Oct 28 12:41:27 +0000 2015", "id_str": "659349254390042624", "timestamp_ms": "1446036087000"}
