{"user": {"name": "live_like_5sos", "id_str": "2895812491"}, "text": "10 second power outage", "created_at": "Sun Oct 25 23:12:20 +0000 2015", "id_str": "658420859112034305", "timestamp_ms": "1445814740000"}
{"user": {"name": "MetroEscalators", "id_str": "1227585284"}, "text": "Broken! #VirginiaSquare #K03X07. Status is Power Outage. Last broke 8 days ago. http://www.dcmetrometrics.com/unit/K03X07ESCALATOR\u00a0\u2026", "created_at": "Sun Oct 25 23:12:18 +0000 2015", "id_str": "658420850056675328", "timestamp_ms": "1445814738000"}
