{"user": {"name": "tofire11", "id_str": "18409921"}, "text": "[1] NY Natural Gas Leak Craigmore Cres b/w Dudley Ave & Willowdale Ave DistrictChief-11 HazMat-145 Pumper-114 Pumper-324 [114]", "created_at": "Tue Oct 27 18:32:41 +0000 2015", "id_str": "659075257723191296", "timestamp_ms": "1445970761000"}
{"user": {"name": "orlandosentinel", "id_str": "1429761"}, "text": "Orlando Sentinel Retweeted Paul Brinkmann", "created_at": "Tue Oct 27 18:32:35 +0000 2015", "id_str": "659075234113437697", "timestamp_ms": "1445970755000"}
