{"user": {"name": "LawCAInjury", "id_str": "2181302706"}, "text": "Man suffers work injury in Highway 1 construction accident: California construction workers face any number of... http://bit.ly/1PZjorw\u00a0", "created_at": "Fri Oct 30 14:23:55 +0000 2015", "id_str": "660099816857309184", "timestamp_ms": "1446215035000"}
{"user": {"name": "alexxxxaaaaaa", "id_str": "234541000"}, "text": "a drunky almost slammed into my uber last night on the highway, inches away from bad accident but alive so let's celebrate!", "created_at": "Fri Oct 30 14:23:31 +0000 2015", "id_str": "660099719125831680", "timestamp_ms": "1446215011000"}
