{"user": {"name": "CityTshwane", "id_str": "149052206"}, "text": "#powerupdate We are aware of a power outage in #LotusGardens. This occurred due to three (3) ring feeder cable faults.", "created_at": "Fri Oct 23 20:42:43 +0000 2015", "id_str": "657658430212149248", "timestamp_ms": "1445632963000"}
{"user": {"name": "BHScanner", "id_str": "289128879"}, "text": "POWER OUTAGE UPDATE: Intermittent outages as far west as Beverwil Dr along Pico Blvd (& residential streets north & south of Pico).", "created_at": "Fri Oct 23 20:42:14 +0000 2015", "id_str": "657658310074761217", "timestamp_ms": "1445632934000"}
