{"user": {"name": "esportsws", "id_str": "1952388158"}, "text": "New post: Power outage disrupts Fox telecast of World Series http://esports.ws/power-outage-disrupts-fox-telecast-of-world-series/\u00a0\u2026", "created_at": "Wed Oct 28 05:46:15 +0000 2015", "id_str": "659244769193758720", "timestamp_ms": "1446011175000"}
{"user": {"name": "The_Djjp", "id_str": "126531683"}, "text": "Fixing the Power outage!\nRAW: Fox crews try to diagnose outage at Kauffman http://www.kctv5.com/clip/11955099/raw-fox-crews-try-to-diagnose-outage-at-kauffman#.VjBgro9Vodk.twitter\u00a0\u2026", "created_at": "Wed Oct 28 05:46:07 +0000 2015", "id_str": "659244734628524032", "timestamp_ms": "1446011167000"}
