{"user": {"name": "ElBroide", "id_str": "31497798"}, "text": "Fuck, guys! This #BridgeCollapse is actually so serious! Every time we drove close to or under the structure, our lives were in danger.", "created_at": "Wed Oct 14 18:26:37 +0000 2015", "id_str": "654362691281231872", "timestamp_ms": "1444847197000"}
{"user": {"name": "SABreakingNews", "id_str": "34908698"}, "text": "Chaos in aftermath of Grayston bridge collapse on M1, Joburg http://www.sabreakingnews.co.za/2015/10/14/chaos-in-aftermath-of-grayston-bridge-collapse-on-m1-joburg/\u00a0\u2026", "created_at": "Wed Oct 14 18:26:37 +0000 2015", "id_str": "654362689297362945", "timestamp_ms": "1444847197000"}
{"user": {"name": "Kei2M", "id_str": "372129603"}, "text": "Oyi..\"@SAfmnews: The death toll from the Sandton bridge collapse on the M1 highway near Grayston Drive has risen to three.\"", "created_at": "Wed Oct 14 18:26:25 +0000 2015", "id_str": "654362640265953281", "timestamp_ms": "1444847185000"}
{"user": {"name": "ewnreporter", "id_str": "191795989"}, "text": "#BridgeCollapse Bystanders on the Grayston Drive Bridge, some are taking pictures of the accident. TK pic.twitter.com/UUh19ZNJde", "created_at": "Wed Oct 14 18:26:22 +0000 2015", "id_str": "654362626898690048", "timestamp_ms": "1444847182000"}
