{"user": {"name": "daijouboobs", "id_str": "437191332"}, "text": "So there was a gas leak at my uni and classes were cancelled until 2:30. Too bad i have class at 6:30 >:[", "created_at": "Mon Oct 05 16:18:58 +0000 2015", "id_str": "651069074374553601", "timestamp_ms": "1444061938000"}
{"user": {"name": "KarenM0213", "id_str": "2230385462"}, "text": "\"The gas leak was called in by the @ManBookerPrize.\" @rickmercer #GillerPrize @agotoronto @TOBookAwards pic.twitter.com/QyD2YE5UJH", "created_at": "Mon Oct 05 16:18:12 +0000 2015", "id_str": "651068882615185413", "timestamp_ms": "1444061892000"}
