{"user": {"name": "Clt_TrafficGuy", "id_str": "485608474"}, "text": "\u25bcI-85 NB near Davidson Highway (NC 73) exit 55, accident reported.\nMinor delays so far #Concord\n#Clt #Traffic pic.twitter.com/z1pSrFPnRO", "created_at": "Fri Oct 09 10:46:51 +0000 2015", "id_str": "652435045131665408", "timestamp_ms": "1444387611000"}
{"user": {"name": "danikasas96", "id_str": "103185087"}, "text": "Omg just witness and accident on the highway holy crap", "created_at": "Fri Oct 09 10:46:18 +0000 2015", "id_str": "652434908376363008", "timestamp_ms": "1444387578000"}
