{"user": {"name": "GavelAlaska", "id_str": "302218753"}, "text": "On #TalkofAK today, @AkGovBillWalker, @GiesselAkSenate, & Sen. Berta Gardner. Talking #AKleg special session and gasline.", "created_at": "Tue Oct 27 18:05:44 +0000 2015", "id_str": "659068476292657152", "timestamp_ms": "1445969144000"}
{"user": {"name": "tayvesp", "id_str": "2160169716"}, "text": "To the lady in line for gas next to me @ Costco stop giving me a weird look. U know ur enjoying me blaring Adele's new song as much as I am.", "created_at": "Tue Oct 27 18:05:10 +0000 2015", "id_str": "659068333778599936", "timestamp_ms": "1445969110000"}
