{"user": {"name": "ABC1230Sports", "id_str": "1621005668"}, "text": "Power Outage Interrupts First World Series Games -  http://abc1230sports.1230thefan.com/2015/10/28/power-outage-interrupts-first-world-series-games/\u00a0\u2026 pic.twitter.com/siBItXMPeG", "created_at": "Wed Oct 28 03:13:56 +0000 2015", "id_str": "659206434161299456", "timestamp_ms": "1446002036000"}
{"user": {"name": "Screamingfrom", "id_str": "459504012"}, "text": "#sports #twitter Power outage disrupts Fox telecast of World Series: (Reuters) - The Fox Sports broadcast of G... http://yhoo.it/1MSuhGm\u00a0", "created_at": "Wed Oct 28 03:13:27 +0000 2015", "id_str": "659206315776983040", "timestamp_ms": "1446002007000"}
{"user": {"name": "publicspeakin99", "id_str": "2841099951"}, "text": "\u26a1\ufe0fPUBLICSPEAKING\u26a1\ufe0f Retweeted ", "created_at": "Wed Oct 28 03:13:12 +0000 2015", "id_str": "659206251641970689", "timestamp_ms": "1446001992000"}
