{"user": {"name": "lcsalegal", "id_str": "2725951783"}, "text": "Bridge collapse inquiry to take at least 6-months - CNBC Africa http://www.cnbcafrica.com/news/southern-africa/2015/10/28/m1-bridge-collapse-preliminary-report/?utm_source=CNBC+Daily+Newsletter&utm_campaign=8294a3df98-RSS_EMAIL_CAMPAIGN_Daily&utm_medium=email&utm_term=0_37ea1a8e5e-8294a3df98-212434181#.VjHg_Zx5XwI.twitter\u00a0\u2026", "created_at": "Thu Oct 29 09:04:03 +0000 2015", "id_str": "659656933104869376", "timestamp_ms": "1446109443000"}
