{"user": {"name": "valkdrow", "id_str": "1217990341"}, "text": "there's a power outage scheduled for my school's area tomorrow im so excited to freeze to death !", "created_at": "Sun Oct 18 20:27:25 +0000 2015", "id_str": "655842642995970048", "timestamp_ms": "1445200045000"}
{"user": {"name": "KyleGovernment", "id_str": "2291339130"}, "text": "911 phones lines in Kyle fully functional. PEC on scene. Estimate ~an hour to resolve power outage.", "created_at": "Sun Oct 18 20:27:24 +0000 2015", "id_str": "655842639552495616", "timestamp_ms": "1445200044000"}
