{"user": {"name": "DavidMcTimoney", "id_str": "345062725"}, "text": "Gibson-Neill Memorial Elementary...closing early today due to power outage.", "created_at": "Fri Oct 30 15:16:08 +0000 2015", "id_str": "660112959352516608", "timestamp_ms": "1446218168000"}
{"user": {"name": "bhsnorseman", "id_str": "191608238"}, "text": "Resourceful students continue to compete in journalism uil event while dealing with a power outage. @LaneBuban pic.twitter.com/r8BL0QovLv", "created_at": "Fri Oct 30 15:16:03 +0000 2015", "id_str": "660112939383324672", "timestamp_ms": "1446218163000"}
