{"user": {"name": "YvetteIDK", "id_str": "634516667"}, "text": "CT Post 30 vehicles still stuck in mud on California highway CT Post This Friday, Oct. 16, 2015 photo Rochelle\u2026 http://dlvr.it/CTdvh1\u00a0", "created_at": "Sun Oct 18 21:11:34 +0000 2015", "id_str": "655853753967357952", "timestamp_ms": "1445202694000"}
{"user": {"name": "kone15hd", "id_str": "2582859890"}, "text": "#KONE 30 vehicles still stuck in mud on California highway - The Seattle Times http://dlvr.it/CTf0vX\u00a0 #losangeles", "created_at": "Sun Oct 18 21:11:13 +0000 2015", "id_str": "655853663647195136", "timestamp_ms": "1445202673000"}
